LICENSE.md
MANIFEST.in
README.md
setup.py
polysquare_travis_container.egg-info/PKG-INFO
polysquare_travis_container.egg-info/SOURCES.txt
polysquare_travis_container.egg-info/dependency_links.txt
polysquare_travis_container.egg-info/entry_points.txt
polysquare_travis_container.egg-info/requires.txt
polysquare_travis_container.egg-info/top_level.txt
polysquare_travis_container.egg-info/zip-safe
psqtraviscontainer/__init__.py
psqtraviscontainer/architecture.py
psqtraviscontainer/common_options.py
psqtraviscontainer/constants.py
psqtraviscontainer/container.py
psqtraviscontainer/create.py
psqtraviscontainer/debian_package.py
psqtraviscontainer/directory.py
psqtraviscontainer/distro.py
psqtraviscontainer/download.py
psqtraviscontainer/linux_container.py
psqtraviscontainer/linux_local_container.py
psqtraviscontainer/osx_container.py
psqtraviscontainer/output.py
psqtraviscontainer/package_system.py
psqtraviscontainer/printer.py
psqtraviscontainer/rootdir.py
psqtraviscontainer/use.py
psqtraviscontainer/util.py
psqtraviscontainer/windows_container.py
test/test_acceptance.py
test/test_unit.py
test/testutil.py