Metadata-Version: 1.1
Name: polysquare-travis-container
Version: 0.0.42
Summary: Polysquare Travis-CI Container Root
Home-page: http://github.com/polysquare/polysquare-travis-container
Author: Sam Spilsbury
Author-email: smspillaz@gmail.com
License: MIT
Keywords: development travis
Platform: UNKNOWN
Classifier: Development Status :: 3 - Alpha
Classifier: Intended Audience :: Developers
Classifier: Topic :: Software Development :: Build Tools
Classifier: License :: OSI Approved :: MIT License
Classifier: Programming Language :: Python :: 3
Classifier: Programming Language :: Python :: 3.3
Classifier: Programming Language :: Python :: 3.4
